  [{
    "name":"root",
    "description":"Metadata applicable to all data elements.",
    "fields":[
      {
        "name": "reported_date",
        "valueType": "date",
        "description": "The date or date-time the observation is reported."
      },
      {
        "name": "reporter_organization_id",
        "valueType": "ID",
        "description": "The identifier of the organization reporting.",
        "note":"Either the reporting organization or the practitioner should be provided."
      },
      {
        "name": "reporter_practitioner_id",
        "valueType": "ID",
        "description": "The identifier of the practitioner reporting.",
        "note":"Either the reporting organization or the practitioner should be provided."
      }
    ]
  },
  {
    "name":"patient",
    "description":"The collection of data elements with demographic information about a patient.",
    "parent":"root",
    "fields":[
      {
        "name":"patient_id",
        "valueType":"ID",
        "description":"Unique identifier assigned to the patient.",
        "required":"required"
      },
      {
        "name":"date_of_birth",
        "description":"The actual or approximate date of birth.",
        "required":"optional",
        "valueType":"date"
      },
      {
        "name":"administrative_gender",
        "description":"Administrative Gender - the gender that the patient is considered to have for administration and record keeping purposes.",
        "required":"required",
        "valueType":"code",
        "permissible":{
          "codeList":[
            "Male",
            "Female",
            "Other",
            "Unknown"
          ]
        },
        "notes": "Codes must align with FHIR Administrative Gender value set (http://hl7.org/fhir/ValueSet/administrative-gender)"
      },
      {
        "name":"race",
        "description":"Concepts classifying the person into a named category of humans sharing common history, traits, geographical origin or nationality. The race codes used to represent these concepts are based upon the CDC Race and Ethnicity Code Set Version 1.0.",
        "valueType":"code",
        "required": "optional",
        "permissible":{
          "codeList":[
            "American Indian or Alaska Native",
            "Asian",
            "Black or African American",
            "Native Hawaiian or Other Pacific Islander",
            "White",
            "Unknown",
            "Asked but no answer"
          ]
        },
        "notes":"Codes from http://hl7.org/fhir/us/core/ValueSet/omb-race-category"
      },
      {
        "name":"ethnicity",
        "description":"Concepts classifying the person into a named category of humans sharing common history, traits, geographical origin or nationality. The ethnicity codes used to represent these concepts are based upon the CDC Race and Ethnicity Code Set Version 1.0.",
        "valueType":"code",
        "required": "optional",
        "permissible":{
          "codeList":[
            "Hispanic or Latino",
            "Non Hispanic or Latino"
          ]
        },
        "notes":"Codes from http://hl7.org/fhir/us/core/ValueSet/omb-ethnicity-category"
      },
      {
        "name":"zip_code",
        "description":"Zip code of the primary residence of the patient.",
        "valueType":"string",
        "required":"required",
        "permissible":{
          "regex":"(^\\d{5}$)|(^\\d{9}$)|(^\\d{5}-\\d{4}$)"
        },
        "notes": "Five digit zip code is acceptable."            
      }
    ]
  },
  {
    "name":"Vital_status",
    "description":"An indicator of whether the patient is alive or dead.",
    "parent":"patient",
    "fields":[
      {
        "name":"patient_id",
        "valueType":"ID",
        "description":"Unique identifier of the patient.",
        "required":"required"
      },
      {
        "name":"vital_status",
        "description":"Donor's last known state of living or deceased.",
        "valueType":"code",
        "required":"required",
        "permissible":{
          "codeList":[
            "Alive",
            "Deceased",
            "Unknown"
          ]

        }
      },
      {
        "name":"cause_of_death",
        "description":"Indicates the cause of a patient's death.",
        "valueType":"code",
        "required": "conditional",
        "permissible":{
          "codeList":[
            "ICD-10 Code",
            "SNOMED-CT code"
          ]
        },
        "notes":"Cause of death is only required to be submitted if the patient is deceased. Mortality coding of COVID-19 with ICD-10 see: https://www.who.int/classifications/icd/COVID-19-coding-icd10.pdf?ua=1"
      },
      {
        "name":"date_of_death",
        "description":"Indicates the actual or approximate date of a patient's death.",
        "valueType":"date",
        "required": "conditional",
        "notes":"Date of death is only required to be submitted if the patient is deceased."
      }
    ]
  },

  {
    "name":"patient_PII",
    "description":"Personally identifiable information about a patient.",
    "parent":"patient",
    "fields":[
      {
        "name":"patient_id",
        "valueType":"ID",
        "description":"Unique identifier of the patient.",
        "required":"required"
      },
      {
        "name":"family_name",
        "description":"The part of a name that links to the genealogy.",
        "valueType":"string"
      },
      {
        "name":"given_name(s)",
        "description":"Given names (not always 'first'). Includes middle names.",
        "valueType":"string"
      },
      {
        "name":"address_line",
        "description":"This component contains the house number, apartment number, street name, street direction, P.O. Box number, delivery hints, and similar address information.",
        "valueType":"string"
      },
      {
        "name":"address_city",
        "description":"The name of the city, town, suburb, village or other community or delivery center.",
        "valueType":"string"
      },
      {
        "name":"address_state",
        "description":"US 2 letter state code.",
        "valueType":"string"
      },
      {
        "name":"primary_phone_number",
        "description":"Preferred phone number for the patient.",
        "valueType":"string"
      }
    ]
  }]